env/bin/activate_this.py
env/lib/python3.10/site-packages/_virtualenv.py
env/lib/python3.10/site-packages/gnupg.py
env/lib/python3.10/site-packages/_distutils_hack/__init__.py
env/lib/python3.10/site-packages/_distutils_hack/override.py
env/lib/python3.10/site-packages/pip/__init__.py
env/lib/python3.10/site-packages/pip/__main__.py
env/lib/python3.10/site-packages/pip/_internal/__init__.py
env/lib/python3.10/site-packages/pip/_internal/build_env.py
env/lib/python3.10/site-packages/pip/_internal/cache.py
env/lib/python3.10/site-packages/pip/_internal/configuration.py
env/lib/python3.10/site-packages/pip/_internal/exceptions.py
env/lib/python3.10/site-packages/pip/_internal/main.py
env/lib/python3.10/site-packages/pip/_internal/pyproject.py
env/lib/python3.10/site-packages/pip/_internal/self_outdated_check.py
env/lib/python3.10/site-packages/pip/_internal/wheel_builder.py
env/lib/python3.10/site-packages/pip/_internal/cli/__init__.py
env/lib/python3.10/site-packages/pip/_internal/cli/autocompletion.py
env/lib/python3.10/site-packages/pip/_internal/cli/base_command.py
env/lib/python3.10/site-packages/pip/_internal/cli/cmdoptions.py
env/lib/python3.10/site-packages/pip/_internal/cli/command_context.py
env/lib/python3.10/site-packages/pip/_internal/cli/main.py
env/lib/python3.10/site-packages/pip/_internal/cli/main_parser.py
env/lib/python3.10/site-packages/pip/_internal/cli/parser.py
env/lib/python3.10/site-packages/pip/_internal/cli/progress_bars.py
env/lib/python3.10/site-packages/pip/_internal/cli/req_command.py
env/lib/python3.10/site-packages/pip/_internal/cli/spinners.py
env/lib/python3.10/site-packages/pip/_internal/cli/status_codes.py
env/lib/python3.10/site-packages/pip/_internal/commands/__init__.py
env/lib/python3.10/site-packages/pip/_internal/commands/cache.py
env/lib/python3.10/site-packages/pip/_internal/commands/check.py
env/lib/python3.10/site-packages/pip/_internal/commands/completion.py
secret_hardsimp-0.0.2.dist-info/METADATA
secret_hardsimp-0.0.2.dist-info/WHEEL
secret_hardsimp-0.0.2.dist-info/licenses/LICENSE
secret_hardsimp-0.0.2.dist-info/RECORD
